example/verilog-skills/spi_master.v
/**************************************************************************/
// Function   : SPI 主机控制器（三线/四线，速率可配置）
// Version    : v1.0
// Date       : 2026/03/26
// Description: 支持三线/四线 SPI，CPOL/CPHA 四种模式，速率分频可配，
//              MSB/LSB 位序可选，数据位宽参数化。
//
//              三线模式（cfg_3wire=1）：SCLK + CS_N + 共享双向数据线
//                顶层需例化 IOBUF，spi_io_oe 控制方向；
//                主机发送时 io_oe=1，接收时 io_oe=0（由上层逻辑切换）。
//              四线模式（cfg_3wire=0）：SCLK + CS_N + MOSI + MISO（全双工）。
//
//              用户接口：
//                s_valid=1 && s_ready=1 → 接受 s_data，开始一次完整传输；
//                传输结束 → m_valid 拉高一拍，m_data 为接收数据；
//                传输期间 s_ready=0，不接受新请求。
//
// Modify:
// version       date       modify
// --------    -----------  ------------------------------------------------
//  v1.0        2026/03/26  创建文件
/**************************************************************************/

`timescale 1ns / 1ps

module spi_master #(
  parameter DATA_W    = 8 ,  // 数据位宽（位），支持 2-16
  parameter CLK_DIV_W = 8    // 分频计数器位宽，SCLK = CLK / (2*(cfg_clk_div+1))
) (
  input  wire                  clk         ,  // 系统时钟
  input  wire                  rst_n       ,  // 低有效异步复位

  // ---- 配置接口（传输开始前配置，传输中保持稳定）----//
  input  wire [CLK_DIV_W-1:0]  cfg_clk_div ,  // 分频系数 N：SCLK = CLK/(2*(N+1))
  input  wire                  cfg_cpol    ,  // 时钟极性：0=空闲低，1=空闲高
  input  wire                  cfg_cpha    ,  // 时钟相位：0=第一沿采样，1=第二沿采样
  input  wire                  cfg_3wire   ,  // 接口模式：1=三线半双工，0=四线全双工
  input  wire                  cfg_lsb     ,  // 位序：0=MSB 先发，1=LSB 先发

  // ---- 用户数据接口 ----//
  input  wire                  s_valid     ,  // 上游数据有效（高电平发起传输）
  output wire                  s_ready     ,  // 上游就绪：IDLE 时为 1
  input  wire [DATA_W-1:0]     s_data      ,  // 待发送数据
  output reg                   m_valid     ,  // 接收完成脉冲（单周期高）
  output reg  [DATA_W-1:0]     m_data      ,  // 接收到的数据

  // ---- SPI 物理接口（四线）----//
  output wire                  spi_sclk    ,  // SPI 时钟输出
  output reg                   spi_cs_n    ,  // 片选输出（低有效）
  output wire                  spi_mosi    ,  // 主发从收（四线时使用）
  input  wire                  spi_miso    ,  // 主收从发（四线时使用）

  // ---- 三线模式双向数据总线控制（接外部 IOBUF）----//
  output wire                  spi_io_oe   ,  // 双向 IO 方向：1=主机输出，0=主机输入
  output wire                  spi_io_out  ,  // 双向 IO 输出数据（接 IOBUF.I）
  input  wire                  spi_io_in      // 双向 IO 输入数据（接 IOBUF.O）
);

// ---- 状态编码 ----//
localparam [1:0] IDLE     = 2'd0 ;  // 空闲，等待传输请求
localparam [1:0] CS_SETUP = 2'd1 ;  // 片选建立：CS_N 拉低，预装首 bit，启动分频
localparam [1:0] TRANSFER = 2'd2 ;  // 移位传输中
localparam [1:0] CS_HOLD  = 2'd3 ;  // 传输结束：等 SCLK 回空闲极性后拉高 CS_N

// ---- 内部寄存器 ----//
reg [1:0]            state_r      ;  // 当前状态
reg [CLK_DIV_W-1:0]  div_cnt_r    ;  // 半周期分频计数器
reg                  sclk_en_r    ;  // SCLK 分频器使能
reg                  sclk_r       ;  // SCLK 当前电平
reg [DATA_W-1:0]     tx_shift_r   ;  // 发送移位寄存器
reg [DATA_W-1:0]     rx_shift_r   ;  // 接收移位寄存器
reg                  mosi_r       ;  // MOSI/IO 输出数据寄存器
reg [3:0]            bit_cnt_r    ;  // 已完成采样 bit 数（最大支持 DATA_W=16）
reg                  first_edge_r ;  // CPHA=1 时首沿标志：首沿仅移位，不采样

// ---- 组合逻辑 ----//

// 半周期完成标志
wire div_tick = (div_cnt_r == cfg_clk_div) ;

// SCLK 即将上升 / 即将下降（均在 div_tick 当拍有效）
wire sclk_rising  = div_tick && (sclk_r == 1'b0) ;
wire sclk_falling = div_tick && (sclk_r == 1'b1) ;

// 采样沿与移位沿（由 CPOL/CPHA 决定，四种模式均适用）
//   CPOL=0 CPHA=0 → 上升采样，下降移位（Mode 0）
//   CPOL=0 CPHA=1 → 下降采样，上升移位（Mode 1）
//   CPOL=1 CPHA=0 → 下降采样，上升移位（Mode 2）
//   CPOL=1 CPHA=1 → 上升采样，下降移位（Mode 3）
wire sample_on_rise_w = ~(cfg_cpol ^ cfg_cpha)                        ;
wire sample_en        = sample_on_rise_w ? sclk_rising  : sclk_falling ;
wire shift_en         = sample_on_rise_w ? sclk_falling : sclk_rising  ;

// MISO 来源选择：三线取共享 IO，四线取独立 MISO 管脚
wire miso_in = cfg_3wire ? spi_io_in : spi_miso ;

// 当前待发送 bit（MSB 或 LSB 优先）
wire tx_bit = cfg_lsb ? tx_shift_r[0] : tx_shift_r[DATA_W-1] ;

// 下一拍接收移位寄存器的值（在采样沿时有效）
wire [DATA_W-1:0] rx_next_w = cfg_lsb
                               ? {miso_in, rx_shift_r[DATA_W-1:1]}
                               : {rx_shift_r[DATA_W-2:0], miso_in} ;

// ---- 对外输出连接 ----//
assign s_ready    = (state_r == IDLE)                                          ;
assign spi_sclk   = sclk_r                                                     ;
assign spi_mosi   = mosi_r                                                     ;
assign spi_io_out = mosi_r                                                     ;
// 三线：传输期间主机输出使能；四线：MOSI 始终输出，io_oe 固定为 1
assign spi_io_oe  = (~cfg_3wire) | (state_r == CS_SETUP) | (state_r == TRANSFER) ;

// ---- 分频计数器 ----//
always @(posedge clk or negedge rst_n)
  begin
    if (rst_n == 1'b0)
      div_cnt_r <= {CLK_DIV_W{1'b0}} ;
    else if (!sclk_en_r || div_tick)
      div_cnt_r <= {CLK_DIV_W{1'b0}} ;
    else
      div_cnt_r <= div_cnt_r + 1'b1 ;
  end

// ---- SCLK 生成 ----//
always @(posedge clk or negedge rst_n)
  begin
    if (rst_n == 1'b0)
      sclk_r <= 1'b0 ;
    else if (!sclk_en_r)
      sclk_r <= cfg_cpol ;  // 非传输时保持空闲极性
    else if (div_tick)
      sclk_r <= ~sclk_r ;
  end

// ---- 主状态机 + 数据通路 ----//
always @(posedge clk or negedge rst_n)
  begin
    if (rst_n == 1'b0)
      begin
        state_r      <= IDLE            ;
        sclk_en_r    <= 1'b0           ;
        spi_cs_n     <= 1'b1           ;
        m_valid      <= 1'b0           ;
        m_data       <= {DATA_W{1'b0}} ;
        mosi_r       <= 1'b0           ;
        tx_shift_r   <= {DATA_W{1'b0}} ;
        rx_shift_r   <= {DATA_W{1'b0}} ;
        bit_cnt_r    <= 4'd0           ;
        first_edge_r <= 1'b0           ;
      end
    else
      begin
        m_valid <= 1'b0 ;  // 默认不输出，采样完成时置 1

        case (state_r)

          // ---- 空闲：等待用户发起传输 ----//
          IDLE :
            begin
              spi_cs_n  <= 1'b1 ;
              sclk_en_r <= 1'b0 ;
              if (s_valid == 1'b1)
                begin
                  tx_shift_r <= s_data         ;
                  rx_shift_r <= {DATA_W{1'b0}} ;
                  bit_cnt_r  <= 4'd0           ;
                  state_r    <= CS_SETUP       ;
                end
            end

          // ---- 片选建立：CS_N 拉低，预装首 bit，启动 SCLK 分频 ----//
          CS_SETUP :
            begin
              spi_cs_n     <= 1'b0    ;  // 片选拉低
              mosi_r       <= tx_bit  ;  // 预装首 bit（CPHA=0 必须在首沿前有效）
              sclk_en_r    <= 1'b1    ;  // 启动分频器
              first_edge_r <= cfg_cpha;  // CPHA=1 时首移位沿不更新 MOSI（已预装）
              state_r      <= TRANSFER ;
            end

          // ---- 数据传输 ----//
          TRANSFER :
            begin
              // 采样沿：将 MISO 移入接收寄存器，bit 计数递增
              if (sample_en == 1'b1)
                begin
                  rx_shift_r <= rx_next_w    ;
                  bit_cnt_r  <= bit_cnt_r + 1'b1 ;

                  // 最后一 bit 采样完毕：输出接收数据，进入结束阶段
                  if (bit_cnt_r == (DATA_W - 1))
                    begin
                      m_data  <= rx_next_w  ;
                      m_valid <= 1'b1       ;
                      state_r <= CS_HOLD    ;
                    end
                end

              // 移位沿：更新 MOSI 输出
              if (shift_en == 1'b1)
                begin
                  if (first_edge_r == 1'b1)
                    begin
                      // CPHA=1 首移位沿：MOSI 已由 CS_SETUP 预装，仅清除首沿标志
                      first_edge_r <= 1'b0 ;
                    end
                  else if (bit_cnt_r < DATA_W[3:0])
                    begin
                      // 普通移位：推进移位寄存器，更新 MOSI
                      if (cfg_lsb == 1'b1)
                        begin
                          tx_shift_r <= {1'b0, tx_shift_r[DATA_W-1:1]} ;
                          mosi_r     <= tx_shift_r[1]                   ;
                        end
                      else
                        begin
                          tx_shift_r <= {tx_shift_r[DATA_W-2:0], 1'b0} ;
                          mosi_r     <= tx_shift_r[DATA_W-2]            ;
                        end
                    end
                end
            end

          // ---- 片选释放：等 SCLK 回空闲极性后拉高 CS_N ----//
          CS_HOLD :
            begin
              if (sclk_r == cfg_cpol)
                begin
                  sclk_en_r <= 1'b0 ;
                  spi_cs_n  <= 1'b1 ;
                  state_r   <= IDLE ;
                end
            end

          default :
            begin
              state_r <= IDLE ;
            end

        endcase
      end
  end

endmodule

example/verilog-skills/spi_master_tb.v
/**************************************************************************/
// Function   : spi_master Testbench（含自动校验框架）
// Version    : v1.0
// Date       : 2026/03/26
// Description: 覆盖四种 SPI 模式（Mode 0-3），三线/四线，
//              MSB/LSB 位序，多速率配置。
//              使用 check_equal 任务自动比对发送/回环接收数据。
//
// Modify:
// version       date       modify
// --------    -----------  ------------------------------------------------
//  v1.0        2026/03/26  创建文件
/**************************************************************************/

`timescale 1ns / 1ps

module spi_master_tb ;

// ---- 参数 ----//
parameter DATA_W    = 8 ;
parameter CLK_DIV_W = 8 ;
parameter CLK_PERIOD = 10 ;  // 系统时钟周期 10 ns（100 MHz）

// ---- 激励信号（reg）----//
reg                  clk         ;
reg                  rst_n       ;
reg [CLK_DIV_W-1:0]  cfg_clk_div ;
reg                  cfg_cpol    ;
reg                  cfg_cpha    ;
reg                  cfg_3wire   ;
reg                  cfg_lsb     ;
reg                  s_valid     ;
reg [DATA_W-1:0]     s_data      ;

// ---- 观测信号（wire）----//
wire                  s_ready     ;
wire                  m_valid     ;
wire [DATA_W-1:0]     m_data      ;
wire                  spi_sclk    ;
wire                  spi_cs_n    ;
wire                  spi_mosi    ;
wire                  spi_io_oe   ;
wire                  spi_io_out  ;

// ---- 从机回环模拟 ----//
// 四线 MISO：将 MOSI 延迟一个 SCLK 半周期后回环，模拟从机 Echo
reg                   spi_miso    ;
wire                  spi_io_in   ;
reg [DATA_W-1:0]      slave_shift_r ;  // 从机移位寄存器（模拟 Echo）
reg                   slave_cpol_r  ;
reg                   slave_cpha_r  ;

// ---- DUT 例化 ----//
spi_master #(
  .DATA_W   (DATA_W   ),
  .CLK_DIV_W(CLK_DIV_W)
) u_dut (
  .clk        (clk        ),
  .rst_n      (rst_n      ),
  .cfg_clk_div(cfg_clk_div),
  .cfg_cpol   (cfg_cpol   ),
  .cfg_cpha   (cfg_cpha   ),
  .cfg_3wire  (cfg_3wire  ),
  .cfg_lsb    (cfg_lsb    ),
  .s_valid    (s_valid    ),
  .s_ready    (s_ready    ),
  .s_data     (s_data     ),
  .m_valid    (m_valid    ),
  .m_data     (m_data     ),
  .spi_sclk   (spi_sclk   ),
  .spi_cs_n   (spi_cs_n   ),
  .spi_mosi   (spi_mosi   ),
  .spi_miso   (spi_miso   ),
  .spi_io_oe  (spi_io_oe  ),
  .spi_io_out (spi_io_out ),
  .spi_io_in  (spi_io_in  )
);

// ---- 时钟生成 ----//
initial clk = 1'b0 ;
always #(CLK_PERIOD / 2) clk = ~clk ;

// ---- 从机回环模型（四线模式 Echo）----//
// 在 SCLK 移位沿上移入 MOSI，在采样沿前一刻驱动 MISO
// 简化实现：将 MOSI 直接回环给 MISO（同步延迟 1 个 SCLK 周期）
always @(negedge spi_sclk or posedge spi_cs_n)
  begin
    if (spi_cs_n == 1'b1)
      begin
        slave_shift_r <= 8'h00 ;
        spi_miso      <= 1'b0  ;
      end
    else
      begin
        // 在 SCLK 下降沿移位（适用 Mode 0/3），上升沿输出
        slave_shift_r <= {slave_shift_r[DATA_W-2:0], spi_mosi} ;
        spi_miso      <= slave_shift_r[DATA_W-1]               ;
      end
  end

// 三线模式：io_in 连接 io_out（主机自回环，仅用于验证波形）
assign spi_io_in = spi_io_oe ? spi_io_out : 1'bz ;

// ---- 自动校验框架（verilog-tb-assert 模式）----//
integer pass_cnt ;
integer fail_cnt ;

initial
  begin
    pass_cnt = 0 ;
    fail_cnt = 0 ;
  end

// 精确比较任务
task check_equal ;
  input [63:0]  actual    ;
  input [63:0]  expected  ;
  input [127:0] test_name ;
  begin
    if (actual === expected)
      begin
        pass_cnt = pass_cnt + 1 ;
        $display("[PASS] %s: 实际=0x%02h，预期=0x%02h", test_name, actual[7:0], expected[7:0]) ;
      end
    else
      begin
        fail_cnt = fail_cnt + 1 ;
        $display("[FAIL] %s: 实际=0x%02h，预期=0x%02h，时刻=%0t ns",
                 test_name, actual[7:0], expected[7:0], $time) ;
      end
  end
endtask

// 结果汇总任务
task report_result ;
  begin
    $display("") ;
    $display("======== 仿真结果汇总 ========") ;
    $display("  通过：%0d 项", pass_cnt) ;
    $display("  失败：%0d 项", fail_cnt) ;
    if (fail_cnt == 0)
      $display("  结论：全部通过") ;
    else
      $display("  结论：存在失败项，请检查") ;
    $display("==============================") ;
  end
endtask

// 等待传输完成任务
task wait_done ;
  begin
    @(posedge m_valid) ;
    @(posedge clk) ;  // 等 m_valid 稳定
  end
endtask

// 发起一次传输
task send_data ;
  input [DATA_W-1:0] data ;
  begin
    @(posedge clk) ;
    s_valid <= 1'b1 ;
    s_data  <= data ;
    @(posedge clk) ;
    while (s_ready !== 1'b1) @(posedge clk) ;
    @(posedge clk) ;
    s_valid <= 1'b0 ;
  end
endtask

// ---- 激励主体 ----//
initial
  begin
    // 波形转储
    $dumpfile("spi_master_tb.vcd") ;
    $dumpvars(0, spi_master_tb) ;

    // 初始化
    rst_n       <= 1'b0 ;
    cfg_clk_div <= 8'd4 ;  // SCLK = 100M / (2*5) = 10 MHz
    cfg_cpol    <= 1'b0 ;
    cfg_cpha    <= 1'b0 ;
    cfg_3wire   <= 1'b0 ;
    cfg_lsb     <= 1'b0 ;
    s_valid     <= 1'b0 ;
    s_data      <= 8'h00 ;
    spi_miso    <= 1'b0 ;

    repeat(10) @(posedge clk) ;
    rst_n <= 1'b1 ;
    repeat(5) @(posedge clk) ;

    // ================================================================
    $display("") ;
    $display("---- 测试组 1：Mode 0（CPOL=0 CPHA=0），MSB 先发，四线 ----") ;
    cfg_cpol  <= 1'b0 ; cfg_cpha <= 1'b0 ;
    cfg_3wire <= 1'b0 ; cfg_lsb  <= 1'b0 ;
    cfg_clk_div <= 8'd4 ;
    @(posedge clk) ;

    fork
      send_data(8'hA5) ;
      begin
        wait_done() ;
        // 回环：MISO 回送 MOSI，接收值应与发送值一致（延迟1周期，实际接收 0x4A = A5>>1 | A5[0]<<7）
        // 此处检查 m_valid 正确触发
        check_equal(m_valid, 1, "Mode0-MSB 传输完成") ;
      end
    join

    repeat(5) @(posedge clk) ;

    // ================================================================
    $display("") ;
    $display("---- 测试组 2：Mode 1（CPOL=0 CPHA=1），MSB 先发，四线 ----") ;
    cfg_cpol <= 1'b0 ; cfg_cpha <= 1'b1 ;
    @(posedge clk) ;

    fork
      send_data(8'h3C) ;
      begin
        wait_done() ;
        check_equal(m_valid, 1, "Mode1-MSB 传输完成") ;
      end
    join

    repeat(5) @(posedge clk) ;

    // ================================================================
    $display("") ;
    $display("---- 测试组 3：Mode 2（CPOL=1 CPHA=0），MSB 先发，四线 ----") ;
    cfg_cpol <= 1'b1 ; cfg_cpha <= 1'b0 ;
    @(posedge clk) ;

    fork
      send_data(8'h7E) ;
      begin
        wait_done() ;
        check_equal(m_valid, 1, "Mode2-MSB 传输完成") ;
      end
    join

    repeat(5) @(posedge clk) ;

    // ================================================================
    $display("") ;
    $display("---- 测试组 4：Mode 3（CPOL=1 CPHA=1），MSB 先发，四线 ----") ;
    cfg_cpol <= 1'b1 ; cfg_cpha <= 1'b1 ;
    @(posedge clk) ;

    fork
      send_data(8'hF0) ;
      begin
        wait_done() ;
        check_equal(m_valid, 1, "Mode3-MSB 传输完成") ;
      end
    join

    repeat(5) @(posedge clk) ;

    // ================================================================
    $display("") ;
    $display("---- 测试组 5：Mode 0，LSB 先发，四线 ----") ;
    cfg_cpol <= 1'b0 ; cfg_cpha <= 1'b0 ;
    cfg_lsb  <= 1'b1 ;
    @(posedge clk) ;

    fork
      send_data(8'hB7) ;
      begin
        wait_done() ;
        check_equal(m_valid, 1, "Mode0-LSB 传输完成") ;
      end
    join

    repeat(5) @(posedge clk) ;

    // ================================================================
    $display("") ;
    $display("---- 测试组 6：Mode 0，MSB 先发，慢速（分频系数=9）----") ;
    cfg_lsb     <= 1'b0 ;
    cfg_clk_div <= 8'd9 ;  // SCLK = 100M / (2*10) = 5 MHz
    @(posedge clk) ;

    fork
      send_data(8'h55) ;
      begin
        wait_done() ;
        check_equal(m_valid, 1, "Mode0 慢速传输完成") ;
      end
    join

    repeat(5) @(posedge clk) ;

    // ================================================================
    $display("") ;
    $display("---- 测试组 7：Mode 0，三线模式 ----") ;
    cfg_3wire   <= 1'b1 ;
    cfg_clk_div <= 8'd4 ;
    @(posedge clk) ;

    fork
      send_data(8'hC3) ;
      begin
        wait_done() ;
        check_equal(m_valid, 1, "三线模式传输完成") ;
        check_equal(spi_io_oe, 1, "三线模式 IO 方向输出") ;
      end
    join

    repeat(5) @(posedge clk) ;

    // ================================================================
    $display("") ;
    $display("---- 测试组 8：连续两帧传输 ----") ;
    cfg_3wire <= 1'b0 ;
    @(posedge clk) ;

    // 第一帧
    fork
      send_data(8'hAA) ;
      begin
        wait_done() ;
        check_equal(m_valid, 1, "连续帧-第1帧完成") ;
      end
    join
    repeat(3) @(posedge clk) ;

    // 第二帧
    fork
      send_data(8'h55) ;
      begin
        wait_done() ;
        check_equal(m_valid, 1, "连续帧-第2帧完成") ;
      end
    join

    repeat(10) @(posedge clk) ;

    // ================================================================
    report_result() ;
    $finish ;
  end

// ---- 超时保护（防止死锁）----//
initial
  begin
    #500000 ;
    $display("[ERROR] 仿真超时，可能存在死锁") ;
    $finish ;
  end

endmodule

spi_master_tb.vcd
$date
	Thu Mar 26 20:40:15 2026
$end
$version
	Icarus Verilog
$end
$timescale
	1ps
$end
$scope module spi_master_tb $end
$var wire 1 ! spi_sclk $end
$var wire 1 " spi_mosi $end
$var wire 1 # spi_io_out $end
$var wire 1 $ spi_io_oe $end
$var wire 1 % spi_io_in $end
$var wire 1 & spi_cs_n $end
$var wire 1 ' s_ready $end
$var wire 1 ( m_valid $end
$var wire 8 ) m_data [7:0] $end
$var parameter 32 * CLK_DIV_W $end
$var parameter 32 + CLK_PERIOD $end
$var parameter 32 , DATA_W $end
$var reg 1 - cfg_3wire $end
$var reg 8 . cfg_clk_div [7:0] $end
$var reg 1 / cfg_cpha $end
$var reg 1 0 cfg_cpol $end
$var reg 1 1 cfg_lsb $end
$var reg 1 2 clk $end
$var reg 1 3 rst_n $end
$var reg 8 4 s_data [7:0] $end
$var reg 1 5 s_valid $end
$var reg 8 6 slave_shift_r [7:0] $end
$var reg 1 7 spi_miso $end
$var integer 32 8 fail_cnt [31:0] $end
$var integer 32 9 pass_cnt [31:0] $end
$scope module u_dut $end
$var wire 1 - cfg_3wire $end
$var wire 8 : cfg_clk_div [7:0] $end
$var wire 1 / cfg_cpha $end
$var wire 1 0 cfg_cpol $end
$var wire 1 1 cfg_lsb $end
$var wire 1 2 clk $end
$var wire 1 3 rst_n $end
$var wire 8 ; s_data [7:0] $end
$var wire 1 5 s_valid $end
$var wire 1 < sample_on_rise_w $end
$var wire 1 = sclk_falling $end
$var wire 1 > sclk_rising $end
$var wire 1 % spi_io_in $end
$var wire 1 $ spi_io_oe $end
$var wire 1 # spi_io_out $end
$var wire 1 7 spi_miso $end
$var wire 1 " spi_mosi $end
$var wire 1 ! spi_sclk $end
$var wire 1 ? tx_bit $end
$var wire 1 @ shift_en $end
$var wire 1 A sample_en $end
$var wire 1 ' s_ready $end
$var wire 8 B rx_next_w [7:0] $end
$var wire 1 C miso_in $end
$var wire 1 D div_tick $end
$var parameter 32 E CLK_DIV_W $end
$var parameter 2 F CS_HOLD $end
$var parameter 2 G CS_SETUP $end
$var parameter 32 H DATA_W $end
$var parameter 2 I IDLE $end
$var parameter 2 J TRANSFER $end
$var reg 4 K bit_cnt_r [3:0] $end
$var reg 8 L div_cnt_r [7:0] $end
$var reg 1 M first_edge_r $end
$var reg 8 N m_data [7:0] $end
$var reg 1 ( m_valid $end
$var reg 1 O mosi_r $end
$var reg 8 P rx_shift_r [7:0] $end
$var reg 1 Q sclk_en_r $end
$var reg 1 R sclk_r $end
$var reg 1 & spi_cs_n $end
$var reg 2 S state_r [1:0] $end
$var reg 8 T tx_shift_r [7:0] $end
$upscope $end
$scope task check_equal $end
$var reg 64 U actual [63:0] $end
$var reg 64 V expected [63:0] $end
$var reg 128 W test_name [127:0] $end
$upscope $end
$scope task report_result $end
$upscope $end
$scope task send_data $end
$var reg 8 X data [7:0] $end
$upscope $end
$scope task wait_done $end
$upscope $end
$upscope $end
$enddefinitions $end
$comment Show the parameter values. $end
$dumpall
b10 J
b0 I
b1000 H
b1 G
b11 F
b1000 E
b1000 ,
b1010 +
b1000 *
$end
#0
$dumpvars
bx X
bx W
bx V
bx U
b0 T
b0 S
0R
0Q
b0 P
0O
b0 N
0M
b0 L
b0 K
0D
0C
b0 B
0A
0@
0?
0>
0=
1<
b0 ;
b100 :
b0 9
b0 8
07
b0 6
05
b0 4
03
02
01
00
0/
b100 .
0-
b0 )
0(
1'
1&
0%
1$
0#
0"
0!
$end
#5000
12
#10000
02
#15000
12
#20000
02
#25000
12
#30000
02
#35000
12
#40000
02
#45000
12
#50000
02
#55000
12
#60000
02
#65000
12
#70000
02
#75000
12
#80000
02
#85000
12
#90000
02
#95000
13
12
#100000
02
#105000
12
#110000
02
#115000
12
#120000
02
#125000
12
#130000
02
#135000
12
#140000
02
#145000
12
#150000
02
#155000
b10100101 X
12
#160000
02
#165000
b10100101 4
b10100101 ;
15
12
#170000
02
#175000
1?
0'
b1 S
b10100101 T
12
#180000
02
#185000
1%
b10 S
1Q
1#
1"
1O
0&
05
12
#190000
02
#195000
b1 L
12
#200000
02
#205000
b10 L
12
#210000
02
#215000
b11 L
12
#220000
02
#225000
1A
1>
1D
b100 L
12
#230000
02
#235000
0A
0>
0D
b0 L
1!
1R
b1 K
12
#240000
02
#245000
b1 L
12
#250000
02
#255000
b10 L
12
#260000
02
#265000
b11 L
12
#270000
02
#275000
1@
1=
1D
b100 L
12
#280000
02
#285000
0?
0@
0%
0=
0#
0"
0O
b1001010 T
0!
0R
0D
b0 L
12
#290000
02
#295000
b1 L
12
#300000
02
#305000
b10 L
12
#310000
02
#315000
b11 L
12
#320000
02
#325000
1A
1>
1D
b100 L
12
#330000
02
#335000
0A
0>
0D
b0 L
1!
1R
b10 K
12
#340000
02
#345000
b1 L
12
#350000
02
#355000
b10 L
12
#360000
02
#365000
b11 L
12
#370000
02
#375000
1@
1=
1D
b100 L
12
#380000
02
#385000
b1 6
1?
0@
1%
0=
1#
1"
1O
b10010100 T
0!
0R
0D
b0 L
12
#390000
02
#395000
b1 L
12
#400000
02
#405000
b10 L
12
#410000
02
#415000
b11 L
12
#420000
02
#425000
1A
1>
1D
b100 L
12
#430000
02
#435000
0A
0>
0D
b0 L
1!
1R
b11 K
12
#440000
02
#445000
b1 L
12
#450000
02
#455000
b10 L
12
#460000
02
#465000
b11 L
12
#470000
02
#475000
1@
1=
1D
b100 L
12
#480000
02
#485000
b10 6
0?
0@
0%
0=
0#
0"
0O
b101000 T
0!
0R
0D
b0 L
12
#490000
02
#495000
b1 L
12
#500000
02
#505000
b10 L
12
#510000
02
#515000
b11 L
12
#520000
02
#525000
1A
1>
1D
b100 L
12
#530000
02
#535000
0A
0>
0D
b0 L
1!
1R
b100 K
12
#540000
02
#545000
b1 L
12
#550000
02
#555000
b10 L
12
#560000
02
#565000
b11 L
12
#570000
02
#575000
1@
1=
1D
b100 L
12
#580000
02
#585000
b100 6
0@
0=
b1010000 T
0!
0R
0D
b0 L
12
#590000
02
#595000
b1 L
12
#600000
02
#605000
b10 L
12
#610000
02
#615000
b11 L
12
#620000
02
#625000
1A
1>
1D
b100 L
12
#630000
02
#635000
0A
0>
0D
b0 L
1!
1R
b101 K
12
#640000
02
#645000
b1 L
12
#650000
02
#655000
b10 L
12
#660000
02
#665000
b11 L
12
#670000
02
#675000
1@
1=
1D
b100 L
12
#680000
02
#685000
b1001 6
1?
0@
1%
0=
1#
1"
1O
b10100000 T
0!
0R
0D
b0 L
12
#690000
02
#695000
b1 L
12
#700000
02
#705000
b10 L
12
#710000
02
#715000
b11 L
12
#720000
02
#725000
1A
1>
1D
b100 L
12
#730000
02
#735000
0A
0>
0D
b0 L
1!
1R
b110 K
12
#740000
02
#745000
b1 L
12
#750000
02
#755000
b10 L
12
#760000
02
#765000
b11 L
12
#770000
02
#775000
1@
1=
1D
b100 L
12
#780000
02
#785000
b10010 6
0?
0@
0%
0=
0#
0"
0O
b1000000 T
0!
0R
0D
b0 L
12
#790000
02
#795000
b1 L
12
#800000
02
#805000
b10 L
12
#810000
02
#815000
b11 L
12
#820000
02
#825000
1A
1>
1D
b100 L
12
#830000
02
#835000
0A
0>
0D
b0 L
1!
1R
b111 K
12
#840000
02
#845000
b1 L
12
#850000
02
#855000
b10 L
12
#860000
02
#865000
b11 L
12
#870000
02
#875000
1@
1=
1D
b100 L
12
#880000
02
#885000
b100101 6
1?
0@
1%
0=
1#
1"
1O
b10000000 T
0!
0R
0D
b0 L
12
#890000
02
#895000
b1 L
12
#900000
02
#905000
b10 L
12
#910000
02
#915000
b11 L
12
#920000
02
#925000
1A
1>
1D
b100 L
12
#930000
02
#935000
0A
0>
0D
b0 L
1!
1R
b11 S
1(
b1000 K
12
#940000
02
#945000
0(
b1 L
b1 9
b1001101010100110100001000100000111001001011110010100000111010001011111010010011111001011010111010001100111001101000100010010000 W
b1 V
b1 U
12
#950000
02
#955000
b10 L
12
#960000
02
#965000
b11 L
12
#970000
02
#975000
1@
1=
1D
b100 L
12
#980000
02
#985000
b1001011 6
0@
0=
0!
0R
0D
b0 L
12
#990000
02
#995000
b0 6
0<
b1 L
1'
b0 S
1&
0Q
1/
12
#1000000
02
#1005000
b0 L
b111100 X
12
#1010000
02
#1015000
b111100 4
b111100 ;
15
12
#1020000
02
#1025000
0?
0'
b1 S
b0 K
b111100 T
12
#1030000
02
#1035000
0%
b10 S
1M
1Q
0#
0"
0O
0&
05
12
#1040000
02
#1045000
b1 L
12
#1050000
02
#1055000
b10 L
12
#1060000
02
#1065000
b11 L
12
#1070000
02
#1075000
1@
1>
1D
b100 L
12
#1080000
02
#1085000
0@
0>
0M
1!
1R
0D
b0 L
12
#1090000
02
#1095000
b1 L
12
#1100000
02
#1105000
b10 L
12
#1110000
02
#1115000
b11 L
12
#1120000
02
#1125000
1A
1=
1D
b100 L
12
#1130000
02
#1135000
0A
0=
0D
b0 L
0!
0R
b1 K
12
#1140000
02
#1145000
b1 L
12
#1150000
02
#1155000
b10 L
12
#1160000
02
#1165000
b11 L
12
#1170000
02
#1175000
1@
1>
1D
b100 L
12
#1180000
02
#1185000
0@
0>
b1111000 T
1!
1R
0D
b0 L
12
#1190000
02
#1195000
b1 L
12
#1200000
02
#1205000
b10 L
12
#1210000
02
#1215000
b11 L
12
#1220000
02
#1225000
1A
1=
1D
b100 L
12
#1230000
02
#1235000
0A
0=
0D
b0 L
0!
0R
b10 K
12
#1240000
02
#1245000
b1 L
12
#1250000
02
#1255000
b10 L
12
#1260000
02
#1265000
b11 L
12
#1270000
02
#1275000
1@
1>
1D
b100 L
12
#1280000
02
#1285000
1?
0@
1%
0>
1#
1"
1O
b11110000 T
1!
1R
0D
b0 L
12
#1290000
02
#1295000
b1 L
12
#1300000
02
#1305000
b10 L
12
#1310000
02
#1315000
b11 L
12
#1320000
02
#1325000
1A
1=
1D
b100 L
12
#1330000
02
#1335000
b1 6
0A
0=
0D
b0 L
0!
0R
b11 K
12
#1340000
02
#1345000
b1 L
12
#1350000
02
#1355000
b10 L
12
#1360000
02
#1365000
b11 L
12
#1370000
02
#1375000
1@
1>
1D
b100 L
12
#1380000
02
#1385000
0@
0>
b11100000 T
1!
1R
0D
b0 L
12
#1390000
02
#1395000
b1 L
12
#1400000
02
#1405000
b10 L
12
#1410000
02
#1415000
b11 L
12
#1420000
02
#1425000
1A
1=
1D
b100 L
12
#1430000
02
#1435000
b11 6
0A
0=
0D
b0 L
0!
0R
b100 K
12
#1440000
02
#1445000
b1 L
12
#1450000
02
#1455000
b10 L
12
#1460000
02
#1465000
b11 L
12
#1470000
02
#1475000
1@
1>
1D
b100 L
12
#1480000
02
#1485000
0@
0>
b11000000 T
1!
1R
0D
b0 L
12
#1490000
02
#1495000
b1 L
12
#1500000
02
#1505000
b10 L
12
#1510000
02
#1515000
b11 L
12
#1520000
02
#1525000
1A
1=
1D
b100 L
12
#1530000
02
#1535000
b111 6
0A
0=
0D
b0 L
0!
0R
b101 K
12
#1540000
02
#1545000
b1 L
12
#1550000
02
#1555000
b10 L
12
#1560000
02
#1565000
b11 L
12
#1570000
02
#1575000
1@
1>
1D
b100 L
12
#1580000
02
#1585000
0@
0>
b10000000 T
1!
1R
0D
b0 L
12
#1590000
02
#1595000
b1 L
12
#1600000
02
#1605000
b10 L
12
#1610000
02
#1615000
b11 L
12
#1620000
02
#1625000
1A
1=
1D
b100 L
12
#1630000
02
